parallelsoup/__init__.py
parallelsoup-2.0.0.dist-info/LICENSE
parallelsoup-2.0.0.dist-info/METADATA
parallelsoup-2.0.0.dist-info/WHEEL
parallelsoup-2.0.0.dist-info/top_level.txt
parallelsoup-2.0.0.dist-info/RECORD
