Metadata-Version: 2.1
Name: parallelsoup
Version: 2.0.0
Summary: A library that utilizes BeautifulSoup to provide multi threaded scrapping, reducing the total time involved in the scrapping process
Home-page: https://github.com/sarthakpranesh/ParallelSoup
Author: Sarthak Pranesh
Author-email: sarthakpranesh08@gmail.com
License: UNKNOWN
Project-URL: Bug Tracker, https://github.com/sarthakpranesh/ParallelSoup/issues
Platform: UNKNOWN
Classifier: Programming Language :: Python :: 3
Classifier: License :: OSI Approved :: MIT License
Classifier: Operating System :: OS Independent
Requires-Python: >=3.6
License-File: LICENSE
